{
  "generated_at": "2026-04-24T08:10:13.381839+00:00",
  "thresholds": {
    "min_coverage": 50.0,
    "min_watch_rankic": 0.025,
    "min_promote_rankic": 0.04,
    "min_promote_stable_count": 2,
    "min_consistency": 55.0,
    "min_promote_orthogonality": 0.15,
    "reject_duplicate_orthogonality": 0.1
  },
  "markets": {
    "a": {
      "market": "a",
      "promote_to_trial": [
        {
          "market": "a",
          "factor": "earnings_accel_proxy",
          "family": "industry",
          "status": "candidate",
          "decision": "PROMOTE_TO_TRIAL",
          "reason": "rankIC、稳定性和正交性均达标，可进入试验池",
          "closest_active_factor": "rev_growth_accel",
          "best_abs_rankic": 0.1626,
          "mean_abs_rankic": 0.1154,
          "stable_count": 3,
          "mean_consistency": 100.0,
          "best_orthogonality": 0.4273,
          "max_coverage": 100.0,
          "quality_score": 29.68,
          "recommended_action": "加入试验回测池，不修改 active 因子池",
          "best_horizon": 30,
          "best_rankic": -0.1626,
          "best_ic": -0.0589,
          "q5_q1_ret_diff_pct": -9.21,
          "q5_q1_up_diff_pp": -18.83,
          "stable_halves": true,
          "first_half_rankic": -0.0585,
          "second_half_rankic": -0.2893
        },
        {
          "market": "a",
          "factor": "gap_ret_20d",
          "family": "behavior",
          "status": "candidate",
          "decision": "PROMOTE_TO_TRIAL",
          "reason": "rankIC、稳定性和正交性均达标，可进入试验池",
          "closest_active_factor": "gap_ret_10d",
          "best_abs_rankic": 0.0712,
          "mean_abs_rankic": 0.0472,
          "stable_count": 2,
          "mean_consistency": 78.3,
          "best_orthogonality": 0.2778,
          "max_coverage": 98.4,
          "quality_score": 19.95,
          "recommended_action": "加入试验回测池，不修改 active 因子池",
          "best_horizon": 10,
          "best_rankic": -0.0712,
          "best_ic": -0.0332,
          "q5_q1_ret_diff_pct": -1.24,
          "q5_q1_up_diff_pp": -10.47,
          "stable_halves": true,
          "first_half_rankic": -0.1045,
          "second_half_rankic": -0.0727
        }
      ],
      "watch": [
        {
          "market": "a",
          "factor": "price_position_z30",
          "family": "behavior",
          "status": "watch",
          "decision": "WATCH",
          "reason": "局部有效且单周期稳定，但整体晋升证据不足，进入观察名单",
          "closest_active_factor": "price_position",
          "best_abs_rankic": 0.0661,
          "mean_abs_rankic": 0.0439,
          "stable_count": 1,
          "mean_consistency": 78.3,
          "best_orthogonality": 0.2574,
          "max_coverage": 94.9,
          "quality_score": 17.17,
          "recommended_action": "保留候选状态，继续观察后续样本",
          "best_horizon": 10,
          "best_rankic": -0.0661,
          "best_ic": -0.0618,
          "q5_q1_ret_diff_pct": -1.66,
          "q5_q1_up_diff_pp": -8.86,
          "stable_halves": true,
          "first_half_rankic": -0.0318,
          "second_half_rankic": -0.1006
        },
        {
          "market": "a",
          "factor": "roc15",
          "family": "trend",
          "status": "watch",
          "decision": "WATCH",
          "reason": "局部有效且单周期稳定，但整体晋升证据不足，进入观察名单",
          "closest_active_factor": "ROC20",
          "best_abs_rankic": 0.0651,
          "mean_abs_rankic": 0.0385,
          "stable_count": 1,
          "mean_consistency": 78.3,
          "best_orthogonality": 0.1421,
          "max_coverage": 97.7,
          "quality_score": 16.33,
          "recommended_action": "保留候选状态，继续观察后续样本",
          "best_horizon": 30,
          "best_rankic": 0.0651,
          "best_ic": 0.0784,
          "q5_q1_ret_diff_pct": 4.5,
          "q5_q1_up_diff_pp": 7.38,
          "stable_halves": true,
          "first_half_rankic": 0.069,
          "second_half_rankic": 0.0457
        },
        {
          "market": "a",
          "factor": "liquidity_stress_proxy",
          "family": "macro",
          "status": "candidate",
          "decision": "WATCH",
          "reason": "局部有效且单周期稳定，但整体晋升证据不足，进入观察名单",
          "closest_active_factor": "gap_ret_10d",
          "best_abs_rankic": 0.053,
          "mean_abs_rankic": 0.03,
          "stable_count": 1,
          "mean_consistency": 71.7,
          "best_orthogonality": 0.3055,
          "max_coverage": 98.4,
          "quality_score": 16.37,
          "recommended_action": "保留候选状态，继续观察后续样本",
          "best_horizon": 10,
          "best_rankic": -0.053,
          "best_ic": -0.0065,
          "q5_q1_ret_diff_pct": -0.81,
          "q5_q1_up_diff_pp": -8.05,
          "stable_halves": true,
          "first_half_rankic": -0.0763,
          "second_half_rankic": -0.048
        },
        {
          "market": "a",
          "factor": "high52w_x_vol_surge",
          "family": "trend",
          "status": "candidate",
          "decision": "WATCH",
          "reason": "局部有效且单周期稳定，但整体晋升证据不足，进入观察名单",
          "closest_active_factor": "high52w_pos",
          "best_abs_rankic": 0.0515,
          "mean_abs_rankic": 0.0477,
          "stable_count": 3,
          "mean_consistency": 100.0,
          "best_orthogonality": 0.1338,
          "max_coverage": 80.7,
          "quality_score": 19.51,
          "recommended_action": "保留候选状态，继续观察后续样本",
          "best_horizon": 10,
          "best_rankic": -0.0515,
          "best_ic": -0.0353,
          "q5_q1_ret_diff_pct": -0.58,
          "q5_q1_up_diff_pp": -7.89,
          "stable_halves": true,
          "first_half_rankic": -0.0471,
          "second_half_rankic": -0.0644
        },
        {
          "market": "a",
          "factor": "price_position_z20",
          "family": "behavior",
          "status": "candidate",
          "decision": "WATCH",
          "reason": "局部有效且单周期稳定，但整体晋升证据不足，进入观察名单",
          "closest_active_factor": "price_position",
          "best_abs_rankic": 0.0461,
          "mean_abs_rankic": 0.0328,
          "stable_count": 1,
          "mean_consistency": 82.2,
          "best_orthogonality": 0.3524,
          "max_coverage": 95.6,
          "quality_score": 16.6,
          "recommended_action": "保留候选状态，继续观察后续样本",
          "best_horizon": 10,
          "best_rankic": -0.0461,
          "best_ic": -0.0548,
          "q5_q1_ret_diff_pct": -1.11,
          "q5_q1_up_diff_pp": -4.81,
          "stable_halves": true,
          "first_half_rankic": -0.0274,
          "second_half_rankic": -0.0651
        },
        {
          "market": "a",
          "factor": "roc60",
          "family": "trend",
          "status": "watch",
          "decision": "WATCH",
          "reason": "局部有效，但稳定性或正交性不足，进入观察名单",
          "closest_active_factor": "high52w_pos",
          "best_abs_rankic": 0.091,
          "mean_abs_rankic": 0.0459,
          "stable_count": 0,
          "mean_consistency": 100.0,
          "best_orthogonality": 0.3516,
          "max_coverage": 90.6,
          "quality_score": 15.41,
          "recommended_action": "保留候选状态，继续观察后续样本",
          "best_horizon": 30,
          "best_rankic": -0.091,
          "best_ic": -0.0049,
          "q5_q1_ret_diff_pct": -2.36,
          "q5_q1_up_diff_pp": -9.62,
          "stable_halves": false,
          "first_half_rankic": -0.2642,
          "second_half_rankic": 0.0827
        },
        {
          "market": "a",
          "factor": "roc30",
          "family": "trend",
          "status": "watch",
          "decision": "WATCH",
          "reason": "局部有效，但稳定性或正交性不足，进入观察名单",
          "closest_active_factor": "ROC20",
          "best_abs_rankic": 0.0742,
          "mean_abs_rankic": 0.0304,
          "stable_count": 0,
          "mean_consistency": 58.9,
          "best_orthogonality": 0.1737,
          "max_coverage": 95.3,
          "quality_score": 13.44,
          "recommended_action": "保留候选状态，继续观察后续样本",
          "best_horizon": 30,
          "best_rankic": 0.0742,
          "best_ic": 0.104,
          "q5_q1_ret_diff_pct": 5.37,
          "q5_q1_up_diff_pp": 10.15,
          "stable_halves": false,
          "first_half_rankic": -0.0105,
          "second_half_rankic": 0.1578
        },
        {
          "market": "a",
          "factor": "price_position_z60",
          "family": "other",
          "status": "watch",
          "decision": "WATCH",
          "reason": "局部有效，但稳定性或正交性不足，进入观察名单",
          "closest_active_factor": "price_position",
          "best_abs_rankic": 0.0511,
          "mean_abs_rankic": 0.0364,
          "stable_count": 0,
          "mean_consistency": 70.0,
          "best_orthogonality": 0.1444,
          "max_coverage": 92.5,
          "quality_score": 13.61,
          "recommended_action": "保留候选状态，继续观察后续样本",
          "best_horizon": 30,
          "best_rankic": 0.0511,
          "best_ic": 0.0465,
          "q5_q1_ret_diff_pct": 1.79,
          "q5_q1_up_diff_pp": 2.49,
          "stable_halves": false,
          "first_half_rankic": 0.1795,
          "second_half_rankic": -0.0961
        },
        {
          "market": "a",
          "factor": "mfdfa_x_vol_surge",
          "family": "industry",
          "status": "watch",
          "decision": "WATCH",
          "reason": "局部有效，但稳定性或正交性不足，进入观察名单",
          "closest_active_factor": "hq2_120d",
          "best_abs_rankic": 0.0484,
          "mean_abs_rankic": 0.0456,
          "stable_count": 0,
          "mean_consistency": 86.7,
          "best_orthogonality": 0.6716,
          "max_coverage": 72.1,
          "quality_score": 15.13,
          "recommended_action": "保留候选状态，继续观察后续样本",
          "best_horizon": 10,
          "best_rankic": -0.0484,
          "best_ic": -0.0547,
          "q5_q1_ret_diff_pct": -1.48,
          "q5_q1_up_diff_pp": -7.08,
          "stable_halves": false,
          "first_half_rankic": -0.1344,
          "second_half_rankic": 0.0713
        }
      ],
      "reject": [
        {
          "market": "a",
          "factor": "ai_mfg_heat_proxy",
          "family": "industry",
          "status": "candidate",
          "decision": "REJECT_DUPLICATE",
          "reason": "与active因子 ROC20 高度重叠",
          "closest_active_factor": "ROC20",
          "best_abs_rankic": 0.0779,
          "mean_abs_rankic": 0.0393,
          "stable_count": 1,
          "mean_consistency": 70.0,
          "best_orthogonality": 0.0529,
          "max_coverage": 96.9,
          "quality_score": 15.88,
          "recommended_action": "记录为重复因子，不建议再次变体试验",
          "best_horizon": 30,
          "best_rankic": 0.0779,
          "best_ic": 0.0912,
          "q5_q1_ret_diff_pct": 5.0,
          "q5_q1_up_diff_pp": 9.31,
          "stable_halves": true,
          "first_half_rankic": 0.0404,
          "second_half_rankic": 0.1002
        },
        {
          "market": "a",
          "factor": "ai_mfg_leader_proxy",
          "family": "industry",
          "status": "candidate",
          "decision": "REJECT_DUPLICATE",
          "reason": "与active因子 ROC20 高度重叠",
          "closest_active_factor": "ROC20",
          "best_abs_rankic": 0.0837,
          "mean_abs_rankic": 0.0383,
          "stable_count": 0,
          "mean_consistency": 68.3,
          "best_orthogonality": 0.0657,
          "max_coverage": 80.7,
          "quality_score": 12.23,
          "recommended_action": "记录为重复因子，不建议再次变体试验",
          "best_horizon": 30,
          "best_rankic": 0.0837,
          "best_ic": 0.068,
          "q5_q1_ret_diff_pct": 3.71,
          "q5_q1_up_diff_pp": 10.68,
          "stable_halves": false,
          "first_half_rankic": 0.0038,
          "second_half_rankic": 0.1535
        },
        {
          "market": "a",
          "factor": "quality_flow_proxy",
          "family": "industry",
          "status": "watch",
          "decision": "REJECT_DUPLICATE",
          "reason": "与active因子 cash_flow_ps 高度重叠",
          "closest_active_factor": "cash_flow_ps",
          "best_abs_rankic": 0.0715,
          "mean_abs_rankic": 0.0333,
          "stable_count": 0,
          "mean_consistency": 63.3,
          "best_orthogonality": 0.0483,
          "max_coverage": 97.0,
          "quality_score": 13.27,
          "recommended_action": "记录为重复因子，不建议再次变体试验",
          "best_horizon": 30,
          "best_rankic": -0.0715,
          "best_ic": -0.0922,
          "q5_q1_ret_diff_pct": -5.02,
          "q5_q1_up_diff_pp": -3.21,
          "stable_halves": false,
          "first_half_rankic": 0.0148,
          "second_half_rankic": -0.1992
        },
        {
          "market": "a",
          "factor": "policy_beta_proxy",
          "family": "macro",
          "status": "candidate",
          "decision": "REJECT_DUPLICATE",
          "reason": "与active因子 price_position 高度重叠",
          "closest_active_factor": "price_position",
          "best_abs_rankic": 0.0584,
          "mean_abs_rankic": 0.0225,
          "stable_count": 0,
          "mean_consistency": 48.3,
          "best_orthogonality": 0.0856,
          "max_coverage": 97.0,
          "quality_score": 12.38,
          "recommended_action": "记录为重复因子，不建议再次变体试验",
          "best_horizon": 30,
          "best_rankic": 0.0584,
          "best_ic": 0.0824,
          "q5_q1_ret_diff_pct": 3.96,
          "q5_q1_up_diff_pp": 5.74,
          "stable_halves": false,
          "first_half_rankic": 0.0855,
          "second_half_rankic": 0.0093
        },
        {
          "market": "a",
          "factor": "intraday_ret_5d",
          "family": "behavior",
          "status": "watch",
          "decision": "REJECT",
          "reason": "信号强度不足",
          "closest_active_factor": "ROC5",
          "best_abs_rankic": 0.0247,
          "mean_abs_rankic": 0.0139,
          "stable_count": 0,
          "mean_consistency": 83.3,
          "best_orthogonality": 0.1538,
          "max_coverage": 99.7,
          "quality_score": 12.13,
          "recommended_action": "淘汰，不进入晋升队列",
          "best_horizon": 10,
          "best_rankic": -0.0247,
          "best_ic": -0.0094,
          "q5_q1_ret_diff_pct": 0.21,
          "q5_q1_up_diff_pp": 0.32,
          "stable_halves": false,
          "first_half_rankic": -0.0151,
          "second_half_rankic": -0.038
        },
        {
          "market": "a",
          "factor": "amihud_30d",
          "family": "behavior",
          "status": "candidate",
          "decision": "REJECT_DUPLICATE",
          "reason": "与active因子 amihud_20d 高度重叠",
          "closest_active_factor": "amihud_20d",
          "best_abs_rankic": 0.0168,
          "mean_abs_rankic": 0.0107,
          "stable_count": 1,
          "mean_consistency": 45.6,
          "best_orthogonality": 0.0275,
          "max_coverage": 97.7,
          "quality_score": 12.98,
          "recommended_action": "记录为重复因子，不建议再次变体试验",
          "best_horizon": 10,
          "best_rankic": -0.0168,
          "best_ic": 0.049,
          "q5_q1_ret_diff_pct": 0.02,
          "q5_q1_up_diff_pp": -6.66,
          "stable_halves": false,
          "first_half_rankic": 0.0026,
          "second_half_rankic": 0.0417
        },
        {
          "market": "a",
          "factor": "gap_ret_5d",
          "family": "behavior",
          "status": "candidate",
          "decision": "REJECT",
          "reason": "信号强度不足",
          "closest_active_factor": "gap_ret_10d",
          "best_abs_rankic": 0.0185,
          "mean_abs_rankic": 0.0102,
          "stable_count": 1,
          "mean_consistency": 64.5,
          "best_orthogonality": 0.272,
          "max_coverage": 99.5,
          "quality_score": 14.33,
          "recommended_action": "淘汰，不进入晋升队列",
          "best_horizon": 10,
          "best_rankic": -0.0185,
          "best_ic": -0.0603,
          "q5_q1_ret_diff_pct": -0.93,
          "q5_q1_up_diff_pp": -6.85,
          "stable_halves": true,
          "first_half_rankic": -0.0417,
          "second_half_rankic": -0.0288
        },
        {
          "market": "a",
          "factor": "mfdfa_x_roc10",
          "family": "fractal",
          "status": "candidate",
          "decision": "REJECT",
          "reason": "信号强度不足",
          "closest_active_factor": "mfdfa_x_roc20",
          "best_abs_rankic": 0.0122,
          "mean_abs_rankic": 0.009,
          "stable_count": 0,
          "mean_consistency": 58.3,
          "best_orthogonality": 0.2819,
          "max_coverage": 72.1,
          "quality_score": 9.52,
          "recommended_action": "淘汰，不进入晋升队列",
          "best_horizon": 10,
          "best_rankic": 0.0122,
          "best_ic": -0.0033,
          "q5_q1_ret_diff_pct": 0.34,
          "q5_q1_up_diff_pp": 2.21,
          "stable_halves": false,
          "first_half_rankic": 0.0185,
          "second_half_rankic": -0.0064
        },
        {
          "market": "a",
          "factor": "amihud_10d",
          "family": "behavior",
          "status": "candidate",
          "decision": "REJECT_DUPLICATE",
          "reason": "与active因子 amihud_20d 高度重叠",
          "closest_active_factor": "amihud_20d",
          "best_abs_rankic": 0.0026,
          "mean_abs_rankic": 0.0012,
          "stable_count": 1,
          "mean_consistency": 41.7,
          "best_orthogonality": 0.0648,
          "max_coverage": 99.2,
          "quality_score": 12.36,
          "recommended_action": "记录为重复因子，不建议再次变体试验",
          "best_horizon": 10,
          "best_rankic": 0.0026,
          "best_ic": 0.0668,
          "q5_q1_ret_diff_pct": 1.25,
          "q5_q1_up_diff_pp": -0.64,
          "stable_halves": false,
          "first_half_rankic": 0.0075,
          "second_half_rankic": 0.0798
        }
      ],
      "counts": {
        "promote_to_trial": 2,
        "watch": 9,
        "reject": 9,
        "total": 20
      },
      "all": [
        {
          "market": "a",
          "factor": "earnings_accel_proxy",
          "family": "industry",
          "status": "candidate",
          "decision": "PROMOTE_TO_TRIAL",
          "reason": "rankIC、稳定性和正交性均达标，可进入试验池",
          "closest_active_factor": "rev_growth_accel",
          "best_abs_rankic": 0.1626,
          "mean_abs_rankic": 0.1154,
          "stable_count": 3,
          "mean_consistency": 100.0,
          "best_orthogonality": 0.4273,
          "max_coverage": 100.0,
          "quality_score": 29.68,
          "recommended_action": "加入试验回测池，不修改 active 因子池",
          "best_horizon": 30,
          "best_rankic": -0.1626,
          "best_ic": -0.0589,
          "q5_q1_ret_diff_pct": -9.21,
          "q5_q1_up_diff_pp": -18.83,
          "stable_halves": true,
          "first_half_rankic": -0.0585,
          "second_half_rankic": -0.2893
        },
        {
          "market": "a",
          "factor": "ai_mfg_heat_proxy",
          "family": "industry",
          "status": "candidate",
          "decision": "REJECT_DUPLICATE",
          "reason": "与active因子 ROC20 高度重叠",
          "closest_active_factor": "ROC20",
          "best_abs_rankic": 0.0779,
          "mean_abs_rankic": 0.0393,
          "stable_count": 1,
          "mean_consistency": 70.0,
          "best_orthogonality": 0.0529,
          "max_coverage": 96.9,
          "quality_score": 15.88,
          "recommended_action": "记录为重复因子，不建议再次变体试验",
          "best_horizon": 30,
          "best_rankic": 0.0779,
          "best_ic": 0.0912,
          "q5_q1_ret_diff_pct": 5.0,
          "q5_q1_up_diff_pp": 9.31,
          "stable_halves": true,
          "first_half_rankic": 0.0404,
          "second_half_rankic": 0.1002
        },
        {
          "market": "a",
          "factor": "gap_ret_20d",
          "family": "behavior",
          "status": "candidate",
          "decision": "PROMOTE_TO_TRIAL",
          "reason": "rankIC、稳定性和正交性均达标，可进入试验池",
          "closest_active_factor": "gap_ret_10d",
          "best_abs_rankic": 0.0712,
          "mean_abs_rankic": 0.0472,
          "stable_count": 2,
          "mean_consistency": 78.3,
          "best_orthogonality": 0.2778,
          "max_coverage": 98.4,
          "quality_score": 19.95,
          "recommended_action": "加入试验回测池，不修改 active 因子池",
          "best_horizon": 10,
          "best_rankic": -0.0712,
          "best_ic": -0.0332,
          "q5_q1_ret_diff_pct": -1.24,
          "q5_q1_up_diff_pp": -10.47,
          "stable_halves": true,
          "first_half_rankic": -0.1045,
          "second_half_rankic": -0.0727
        },
        {
          "market": "a",
          "factor": "price_position_z30",
          "family": "behavior",
          "status": "watch",
          "decision": "WATCH",
          "reason": "局部有效且单周期稳定，但整体晋升证据不足，进入观察名单",
          "closest_active_factor": "price_position",
          "best_abs_rankic": 0.0661,
          "mean_abs_rankic": 0.0439,
          "stable_count": 1,
          "mean_consistency": 78.3,
          "best_orthogonality": 0.2574,
          "max_coverage": 94.9,
          "quality_score": 17.17,
          "recommended_action": "保留候选状态，继续观察后续样本",
          "best_horizon": 10,
          "best_rankic": -0.0661,
          "best_ic": -0.0618,
          "q5_q1_ret_diff_pct": -1.66,
          "q5_q1_up_diff_pp": -8.86,
          "stable_halves": true,
          "first_half_rankic": -0.0318,
          "second_half_rankic": -0.1006
        },
        {
          "market": "a",
          "factor": "roc15",
          "family": "trend",
          "status": "watch",
          "decision": "WATCH",
          "reason": "局部有效且单周期稳定，但整体晋升证据不足，进入观察名单",
          "closest_active_factor": "ROC20",
          "best_abs_rankic": 0.0651,
          "mean_abs_rankic": 0.0385,
          "stable_count": 1,
          "mean_consistency": 78.3,
          "best_orthogonality": 0.1421,
          "max_coverage": 97.7,
          "quality_score": 16.33,
          "recommended_action": "保留候选状态，继续观察后续样本",
          "best_horizon": 30,
          "best_rankic": 0.0651,
          "best_ic": 0.0784,
          "q5_q1_ret_diff_pct": 4.5,
          "q5_q1_up_diff_pp": 7.38,
          "stable_halves": true,
          "first_half_rankic": 0.069,
          "second_half_rankic": 0.0457
        },
        {
          "market": "a",
          "factor": "liquidity_stress_proxy",
          "family": "macro",
          "status": "candidate",
          "decision": "WATCH",
          "reason": "局部有效且单周期稳定，但整体晋升证据不足，进入观察名单",
          "closest_active_factor": "gap_ret_10d",
          "best_abs_rankic": 0.053,
          "mean_abs_rankic": 0.03,
          "stable_count": 1,
          "mean_consistency": 71.7,
          "best_orthogonality": 0.3055,
          "max_coverage": 98.4,
          "quality_score": 16.37,
          "recommended_action": "保留候选状态，继续观察后续样本",
          "best_horizon": 10,
          "best_rankic": -0.053,
          "best_ic": -0.0065,
          "q5_q1_ret_diff_pct": -0.81,
          "q5_q1_up_diff_pp": -8.05,
          "stable_halves": true,
          "first_half_rankic": -0.0763,
          "second_half_rankic": -0.048
        },
        {
          "market": "a",
          "factor": "high52w_x_vol_surge",
          "family": "trend",
          "status": "candidate",
          "decision": "WATCH",
          "reason": "局部有效且单周期稳定，但整体晋升证据不足，进入观察名单",
          "closest_active_factor": "high52w_pos",
          "best_abs_rankic": 0.0515,
          "mean_abs_rankic": 0.0477,
          "stable_count": 3,
          "mean_consistency": 100.0,
          "best_orthogonality": 0.1338,
          "max_coverage": 80.7,
          "quality_score": 19.51,
          "recommended_action": "保留候选状态，继续观察后续样本",
          "best_horizon": 10,
          "best_rankic": -0.0515,
          "best_ic": -0.0353,
          "q5_q1_ret_diff_pct": -0.58,
          "q5_q1_up_diff_pp": -7.89,
          "stable_halves": true,
          "first_half_rankic": -0.0471,
          "second_half_rankic": -0.0644
        },
        {
          "market": "a",
          "factor": "price_position_z20",
          "family": "behavior",
          "status": "candidate",
          "decision": "WATCH",
          "reason": "局部有效且单周期稳定，但整体晋升证据不足，进入观察名单",
          "closest_active_factor": "price_position",
          "best_abs_rankic": 0.0461,
          "mean_abs_rankic": 0.0328,
          "stable_count": 1,
          "mean_consistency": 82.2,
          "best_orthogonality": 0.3524,
          "max_coverage": 95.6,
          "quality_score": 16.6,
          "recommended_action": "保留候选状态，继续观察后续样本",
          "best_horizon": 10,
          "best_rankic": -0.0461,
          "best_ic": -0.0548,
          "q5_q1_ret_diff_pct": -1.11,
          "q5_q1_up_diff_pp": -4.81,
          "stable_halves": true,
          "first_half_rankic": -0.0274,
          "second_half_rankic": -0.0651
        },
        {
          "market": "a",
          "factor": "roc60",
          "family": "trend",
          "status": "watch",
          "decision": "WATCH",
          "reason": "局部有效，但稳定性或正交性不足，进入观察名单",
          "closest_active_factor": "high52w_pos",
          "best_abs_rankic": 0.091,
          "mean_abs_rankic": 0.0459,
          "stable_count": 0,
          "mean_consistency": 100.0,
          "best_orthogonality": 0.3516,
          "max_coverage": 90.6,
          "quality_score": 15.41,
          "recommended_action": "保留候选状态，继续观察后续样本",
          "best_horizon": 30,
          "best_rankic": -0.091,
          "best_ic": -0.0049,
          "q5_q1_ret_diff_pct": -2.36,
          "q5_q1_up_diff_pp": -9.62,
          "stable_halves": false,
          "first_half_rankic": -0.2642,
          "second_half_rankic": 0.0827
        },
        {
          "market": "a",
          "factor": "ai_mfg_leader_proxy",
          "family": "industry",
          "status": "candidate",
          "decision": "REJECT_DUPLICATE",
          "reason": "与active因子 ROC20 高度重叠",
          "closest_active_factor": "ROC20",
          "best_abs_rankic": 0.0837,
          "mean_abs_rankic": 0.0383,
          "stable_count": 0,
          "mean_consistency": 68.3,
          "best_orthogonality": 0.0657,
          "max_coverage": 80.7,
          "quality_score": 12.23,
          "recommended_action": "记录为重复因子，不建议再次变体试验",
          "best_horizon": 30,
          "best_rankic": 0.0837,
          "best_ic": 0.068,
          "q5_q1_ret_diff_pct": 3.71,
          "q5_q1_up_diff_pp": 10.68,
          "stable_halves": false,
          "first_half_rankic": 0.0038,
          "second_half_rankic": 0.1535
        },
        {
          "market": "a",
          "factor": "roc30",
          "family": "trend",
          "status": "watch",
          "decision": "WATCH",
          "reason": "局部有效，但稳定性或正交性不足，进入观察名单",
          "closest_active_factor": "ROC20",
          "best_abs_rankic": 0.0742,
          "mean_abs_rankic": 0.0304,
          "stable_count": 0,
          "mean_consistency": 58.9,
          "best_orthogonality": 0.1737,
          "max_coverage": 95.3,
          "quality_score": 13.44,
          "recommended_action": "保留候选状态，继续观察后续样本",
          "best_horizon": 30,
          "best_rankic": 0.0742,
          "best_ic": 0.104,
          "q5_q1_ret_diff_pct": 5.37,
          "q5_q1_up_diff_pp": 10.15,
          "stable_halves": false,
          "first_half_rankic": -0.0105,
          "second_half_rankic": 0.1578
        },
        {
          "market": "a",
          "factor": "quality_flow_proxy",
          "family": "industry",
          "status": "watch",
          "decision": "REJECT_DUPLICATE",
          "reason": "与active因子 cash_flow_ps 高度重叠",
          "closest_active_factor": "cash_flow_ps",
          "best_abs_rankic": 0.0715,
          "mean_abs_rankic": 0.0333,
          "stable_count": 0,
          "mean_consistency": 63.3,
          "best_orthogonality": 0.0483,
          "max_coverage": 97.0,
          "quality_score": 13.27,
          "recommended_action": "记录为重复因子，不建议再次变体试验",
          "best_horizon": 30,
          "best_rankic": -0.0715,
          "best_ic": -0.0922,
          "q5_q1_ret_diff_pct": -5.02,
          "q5_q1_up_diff_pp": -3.21,
          "stable_halves": false,
          "first_half_rankic": 0.0148,
          "second_half_rankic": -0.1992
        },
        {
          "market": "a",
          "factor": "policy_beta_proxy",
          "family": "macro",
          "status": "candidate",
          "decision": "REJECT_DUPLICATE",
          "reason": "与active因子 price_position 高度重叠",
          "closest_active_factor": "price_position",
          "best_abs_rankic": 0.0584,
          "mean_abs_rankic": 0.0225,
          "stable_count": 0,
          "mean_consistency": 48.3,
          "best_orthogonality": 0.0856,
          "max_coverage": 97.0,
          "quality_score": 12.38,
          "recommended_action": "记录为重复因子，不建议再次变体试验",
          "best_horizon": 30,
          "best_rankic": 0.0584,
          "best_ic": 0.0824,
          "q5_q1_ret_diff_pct": 3.96,
          "q5_q1_up_diff_pp": 5.74,
          "stable_halves": false,
          "first_half_rankic": 0.0855,
          "second_half_rankic": 0.0093
        },
        {
          "market": "a",
          "factor": "price_position_z60",
          "family": "other",
          "status": "watch",
          "decision": "WATCH",
          "reason": "局部有效，但稳定性或正交性不足，进入观察名单",
          "closest_active_factor": "price_position",
          "best_abs_rankic": 0.0511,
          "mean_abs_rankic": 0.0364,
          "stable_count": 0,
          "mean_consistency": 70.0,
          "best_orthogonality": 0.1444,
          "max_coverage": 92.5,
          "quality_score": 13.61,
          "recommended_action": "保留候选状态，继续观察后续样本",
          "best_horizon": 30,
          "best_rankic": 0.0511,
          "best_ic": 0.0465,
          "q5_q1_ret_diff_pct": 1.79,
          "q5_q1_up_diff_pp": 2.49,
          "stable_halves": false,
          "first_half_rankic": 0.1795,
          "second_half_rankic": -0.0961
        },
        {
          "market": "a",
          "factor": "mfdfa_x_vol_surge",
          "family": "industry",
          "status": "watch",
          "decision": "WATCH",
          "reason": "局部有效，但稳定性或正交性不足，进入观察名单",
          "closest_active_factor": "hq2_120d",
          "best_abs_rankic": 0.0484,
          "mean_abs_rankic": 0.0456,
          "stable_count": 0,
          "mean_consistency": 86.7,
          "best_orthogonality": 0.6716,
          "max_coverage": 72.1,
          "quality_score": 15.13,
          "recommended_action": "保留候选状态，继续观察后续样本",
          "best_horizon": 10,
          "best_rankic": -0.0484,
          "best_ic": -0.0547,
          "q5_q1_ret_diff_pct": -1.48,
          "q5_q1_up_diff_pp": -7.08,
          "stable_halves": false,
          "first_half_rankic": -0.1344,
          "second_half_rankic": 0.0713
        },
        {
          "market": "a",
          "factor": "intraday_ret_5d",
          "family": "behavior",
          "status": "watch",
          "decision": "REJECT",
          "reason": "信号强度不足",
          "closest_active_factor": "ROC5",
          "best_abs_rankic": 0.0247,
          "mean_abs_rankic": 0.0139,
          "stable_count": 0,
          "mean_consistency": 83.3,
          "best_orthogonality": 0.1538,
          "max_coverage": 99.7,
          "quality_score": 12.13,
          "recommended_action": "淘汰，不进入晋升队列",
          "best_horizon": 10,
          "best_rankic": -0.0247,
          "best_ic": -0.0094,
          "q5_q1_ret_diff_pct": 0.21,
          "q5_q1_up_diff_pp": 0.32,
          "stable_halves": false,
          "first_half_rankic": -0.0151,
          "second_half_rankic": -0.038
        },
        {
          "market": "a",
          "factor": "amihud_30d",
          "family": "behavior",
          "status": "candidate",
          "decision": "REJECT_DUPLICATE",
          "reason": "与active因子 amihud_20d 高度重叠",
          "closest_active_factor": "amihud_20d",
          "best_abs_rankic": 0.0168,
          "mean_abs_rankic": 0.0107,
          "stable_count": 1,
          "mean_consistency": 45.6,
          "best_orthogonality": 0.0275,
          "max_coverage": 97.7,
          "quality_score": 12.98,
          "recommended_action": "记录为重复因子，不建议再次变体试验",
          "best_horizon": 10,
          "best_rankic": -0.0168,
          "best_ic": 0.049,
          "q5_q1_ret_diff_pct": 0.02,
          "q5_q1_up_diff_pp": -6.66,
          "stable_halves": false,
          "first_half_rankic": 0.0026,
          "second_half_rankic": 0.0417
        },
        {
          "market": "a",
          "factor": "gap_ret_5d",
          "family": "behavior",
          "status": "candidate",
          "decision": "REJECT",
          "reason": "信号强度不足",
          "closest_active_factor": "gap_ret_10d",
          "best_abs_rankic": 0.0185,
          "mean_abs_rankic": 0.0102,
          "stable_count": 1,
          "mean_consistency": 64.5,
          "best_orthogonality": 0.272,
          "max_coverage": 99.5,
          "quality_score": 14.33,
          "recommended_action": "淘汰，不进入晋升队列",
          "best_horizon": 10,
          "best_rankic": -0.0185,
          "best_ic": -0.0603,
          "q5_q1_ret_diff_pct": -0.93,
          "q5_q1_up_diff_pp": -6.85,
          "stable_halves": true,
          "first_half_rankic": -0.0417,
          "second_half_rankic": -0.0288
        },
        {
          "market": "a",
          "factor": "mfdfa_x_roc10",
          "family": "fractal",
          "status": "candidate",
          "decision": "REJECT",
          "reason": "信号强度不足",
          "closest_active_factor": "mfdfa_x_roc20",
          "best_abs_rankic": 0.0122,
          "mean_abs_rankic": 0.009,
          "stable_count": 0,
          "mean_consistency": 58.3,
          "best_orthogonality": 0.2819,
          "max_coverage": 72.1,
          "quality_score": 9.52,
          "recommended_action": "淘汰，不进入晋升队列",
          "best_horizon": 10,
          "best_rankic": 0.0122,
          "best_ic": -0.0033,
          "q5_q1_ret_diff_pct": 0.34,
          "q5_q1_up_diff_pp": 2.21,
          "stable_halves": false,
          "first_half_rankic": 0.0185,
          "second_half_rankic": -0.0064
        },
        {
          "market": "a",
          "factor": "amihud_10d",
          "family": "behavior",
          "status": "candidate",
          "decision": "REJECT_DUPLICATE",
          "reason": "与active因子 amihud_20d 高度重叠",
          "closest_active_factor": "amihud_20d",
          "best_abs_rankic": 0.0026,
          "mean_abs_rankic": 0.0012,
          "stable_count": 1,
          "mean_consistency": 41.7,
          "best_orthogonality": 0.0648,
          "max_coverage": 99.2,
          "quality_score": 12.36,
          "recommended_action": "记录为重复因子，不建议再次变体试验",
          "best_horizon": 10,
          "best_rankic": 0.0026,
          "best_ic": 0.0668,
          "q5_q1_ret_diff_pct": 1.25,
          "q5_q1_up_diff_pp": -0.64,
          "stable_halves": false,
          "first_half_rankic": 0.0075,
          "second_half_rankic": 0.0798
        }
      ]
    },
    "us": {
      "market": "us",
      "promote_to_trial": [
        {
          "market": "us",
          "factor": "vix_ma20_diff_x_roc20",
          "family": "macro",
          "status": "watch",
          "decision": "PROMOTE_TO_TRIAL",
          "reason": "rankIC、稳定性和正交性均达标，可进入试验池",
          "closest_active_factor": "adx_accel",
          "best_abs_rankic": 0.0419,
          "mean_abs_rankic": 0.0331,
          "stable_count": 3,
          "mean_consistency": 84.7,
          "best_orthogonality": 0.8043,
          "max_coverage": 83.0,
          "quality_score": 21.63,
          "recommended_action": "加入试验回测池，不修改 active 因子池",
          "best_horizon": 5,
          "best_rankic": -0.0419,
          "best_ic": -0.0196,
          "q5_q1_ret_diff_pct": -0.73,
          "q5_q1_up_diff_pp": -6.2,
          "stable_halves": true,
          "first_half_rankic": -0.0306,
          "second_half_rankic": -0.0554
        }
      ],
      "watch": [
        {
          "market": "us",
          "factor": "vix_z20_z20",
          "family": "macro",
          "status": "watch",
          "decision": "WATCH",
          "reason": "局部有效且单周期稳定，但整体晋升证据不足，进入观察名单",
          "closest_active_factor": "vix_z20",
          "best_abs_rankic": 0.0451,
          "mean_abs_rankic": 0.0294,
          "stable_count": 1,
          "mean_consistency": 75.5,
          "best_orthogonality": 0.1956,
          "max_coverage": 82.3,
          "quality_score": 14.15,
          "recommended_action": "保留候选状态，继续观察后续样本",
          "best_horizon": 10,
          "best_rankic": -0.0451,
          "best_ic": -0.0408,
          "q5_q1_ret_diff_pct": -1.4,
          "q5_q1_up_diff_pp": -6.41,
          "stable_halves": true,
          "first_half_rankic": -0.0397,
          "second_half_rankic": -0.0588
        },
        {
          "market": "us",
          "factor": "high52w_x_vol_surge",
          "family": "trend",
          "status": "candidate",
          "decision": "WATCH",
          "reason": "局部有效，但稳定性或正交性不足，进入观察名单",
          "closest_active_factor": "high52w_pos",
          "best_abs_rankic": 0.05,
          "mean_abs_rankic": 0.0312,
          "stable_count": 0,
          "mean_consistency": 42.1,
          "best_orthogonality": 0.1362,
          "max_coverage": 87.6,
          "quality_score": 12.56,
          "recommended_action": "保留候选状态，继续观察后续样本",
          "best_horizon": 30,
          "best_rankic": 0.05,
          "best_ic": 0.0678,
          "q5_q1_ret_diff_pct": 2.61,
          "q5_q1_up_diff_pp": 10.37,
          "stable_halves": false,
          "first_half_rankic": 0.0181,
          "second_half_rankic": -0.0551
        },
        {
          "market": "us",
          "factor": "gap_ret_15d",
          "family": "behavior",
          "status": "watch",
          "decision": "WATCH",
          "reason": "局部有效，但稳定性或正交性不足，进入观察名单",
          "closest_active_factor": "ROC20",
          "best_abs_rankic": 0.0491,
          "mean_abs_rankic": 0.0361,
          "stable_count": 0,
          "mean_consistency": 61.1,
          "best_orthogonality": 0.3777,
          "max_coverage": 99.3,
          "quality_score": 15.43,
          "recommended_action": "保留候选状态，继续观察后续样本",
          "best_horizon": 10,
          "best_rankic": 0.0491,
          "best_ic": 0.1284,
          "q5_q1_ret_diff_pct": 2.34,
          "q5_q1_up_diff_pp": 6.55,
          "stable_halves": false,
          "first_half_rankic": -0.0392,
          "second_half_rankic": 0.1006
        },
        {
          "market": "us",
          "factor": "vix_z20_x_atr_pct",
          "family": "macro",
          "status": "candidate",
          "decision": "WATCH",
          "reason": "局部有效，但稳定性或正交性不足，进入观察名单",
          "closest_active_factor": "vix_z20",
          "best_abs_rankic": 0.0429,
          "mean_abs_rankic": 0.0202,
          "stable_count": 0,
          "mean_consistency": 78.2,
          "best_orthogonality": 0.1378,
          "max_coverage": 83.1,
          "quality_score": 11.02,
          "recommended_action": "保留候选状态，继续观察后续样本",
          "best_horizon": 10,
          "best_rankic": -0.0429,
          "best_ic": -0.0202,
          "q5_q1_ret_diff_pct": -0.98,
          "q5_q1_up_diff_pp": -3.18,
          "stable_halves": false,
          "first_half_rankic": 0.0115,
          "second_half_rankic": -0.1026
        },
        {
          "market": "us",
          "factor": "gap_ret_10d",
          "family": "behavior",
          "status": "watch",
          "decision": "WATCH",
          "reason": "局部有效，但稳定性或正交性不足，进入观察名单",
          "closest_active_factor": "ROC20",
          "best_abs_rankic": 0.0373,
          "mean_abs_rankic": 0.0274,
          "stable_count": 0,
          "mean_consistency": 61.7,
          "best_orthogonality": 0.4557,
          "max_coverage": 99.5,
          "quality_score": 14.97,
          "recommended_action": "保留候选状态，继续观察后续样本",
          "best_horizon": 30,
          "best_rankic": 0.0373,
          "best_ic": 0.0861,
          "q5_q1_ret_diff_pct": 4.97,
          "q5_q1_up_diff_pp": 7.48,
          "stable_halves": false,
          "first_half_rankic": -0.007,
          "second_half_rankic": 0.0438
        },
        {
          "market": "us",
          "factor": "gap_ret_8d",
          "family": "behavior",
          "status": "watch",
          "decision": "WATCH",
          "reason": "局部有效，但稳定性或正交性不足，进入观察名单",
          "closest_active_factor": "ROC20",
          "best_abs_rankic": 0.036,
          "mean_abs_rankic": 0.0249,
          "stable_count": 0,
          "mean_consistency": 55.6,
          "best_orthogonality": 0.5019,
          "max_coverage": 99.6,
          "quality_score": 14.96,
          "recommended_action": "保留候选状态，继续观察后续样本",
          "best_horizon": 30,
          "best_rankic": 0.036,
          "best_ic": 0.0848,
          "q5_q1_ret_diff_pct": 4.88,
          "q5_q1_up_diff_pp": 7.25,
          "stable_halves": false,
          "first_half_rankic": -0.0047,
          "second_half_rankic": 0.0424
        },
        {
          "market": "us",
          "factor": "roc60",
          "family": "trend",
          "status": "watch",
          "decision": "WATCH",
          "reason": "局部有效，但稳定性或正交性不足，进入观察名单",
          "closest_active_factor": "DIF",
          "best_abs_rankic": 0.0327,
          "mean_abs_rankic": 0.0198,
          "stable_count": 0,
          "mean_consistency": 63.9,
          "best_orthogonality": 0.3328,
          "max_coverage": 94.0,
          "quality_score": 13.04,
          "recommended_action": "保留候选状态，继续观察后续样本",
          "best_horizon": 30,
          "best_rankic": -0.0327,
          "best_ic": 0.0451,
          "q5_q1_ret_diff_pct": 2.73,
          "q5_q1_up_diff_pp": 4.15,
          "stable_halves": false,
          "first_half_rankic": 0.0196,
          "second_half_rankic": -0.1146
        },
        {
          "market": "us",
          "factor": "vol_change_z20",
          "family": "other",
          "status": "watch",
          "decision": "WATCH",
          "reason": "局部有效，但稳定性或正交性不足，进入观察名单",
          "closest_active_factor": "vol_surge",
          "best_abs_rankic": 0.03,
          "mean_abs_rankic": 0.0192,
          "stable_count": 0,
          "mean_consistency": 61.9,
          "best_orthogonality": 0.2188,
          "max_coverage": 98.2,
          "quality_score": 12.83,
          "recommended_action": "保留候选状态，继续观察后续样本",
          "best_horizon": 30,
          "best_rankic": 0.03,
          "best_ic": 0.0482,
          "q5_q1_ret_diff_pct": 3.11,
          "q5_q1_up_diff_pp": 4.61,
          "stable_halves": false,
          "first_half_rankic": -0.014,
          "second_half_rankic": 0.0616
        },
        {
          "market": "us",
          "factor": "gap_ret_5d",
          "family": "behavior",
          "status": "candidate",
          "decision": "WATCH",
          "reason": "局部有效，但稳定性或正交性不足，进入观察名单",
          "closest_active_factor": "-DI",
          "best_abs_rankic": 0.0287,
          "mean_abs_rankic": 0.0162,
          "stable_count": 0,
          "mean_consistency": 50.0,
          "best_orthogonality": 0.5751,
          "max_coverage": 99.7,
          "quality_score": 14.47,
          "recommended_action": "保留候选状态，继续观察后续样本",
          "best_horizon": 30,
          "best_rankic": 0.0287,
          "best_ic": 0.0718,
          "q5_q1_ret_diff_pct": 3.98,
          "q5_q1_up_diff_pp": 5.51,
          "stable_halves": false,
          "first_half_rankic": -0.0064,
          "second_half_rankic": 0.0362
        },
        {
          "market": "us",
          "factor": "gap_ret_3d",
          "family": "behavior",
          "status": "watch",
          "decision": "WATCH",
          "reason": "局部有效，但稳定性或正交性不足，进入观察名单",
          "closest_active_factor": "-DI",
          "best_abs_rankic": 0.0259,
          "mean_abs_rankic": 0.0161,
          "stable_count": 0,
          "mean_consistency": 60.0,
          "best_orthogonality": 0.6318,
          "max_coverage": 99.7,
          "quality_score": 14.74,
          "recommended_action": "保留候选状态，继续观察后续样本",
          "best_horizon": 30,
          "best_rankic": 0.0259,
          "best_ic": 0.0566,
          "q5_q1_ret_diff_pct": 3.72,
          "q5_q1_up_diff_pp": 3.33,
          "stable_halves": false,
          "first_half_rankic": 0.0023,
          "second_half_rankic": 0.0296
        },
        {
          "market": "us",
          "factor": "vol_change_x_high52w",
          "family": "industry",
          "status": "watch",
          "decision": "WATCH",
          "reason": "局部有效且单周期稳定，但整体晋升证据不足，进入观察名单",
          "closest_active_factor": "vol_surge",
          "best_abs_rankic": 0.032,
          "mean_abs_rankic": 0.0246,
          "stable_count": 1,
          "mean_consistency": 59.3,
          "best_orthogonality": 0.1183,
          "max_coverage": 87.6,
          "quality_score": 13.81,
          "recommended_action": "保留候选状态，继续观察后续样本",
          "best_horizon": 30,
          "best_rankic": 0.032,
          "best_ic": 0.0767,
          "q5_q1_ret_diff_pct": 3.39,
          "q5_q1_up_diff_pp": 3.61,
          "stable_halves": true,
          "first_half_rankic": 0.0424,
          "second_half_rankic": 0.0549
        },
        {
          "market": "us",
          "factor": "vix_z20_x_high52w",
          "family": "macro",
          "status": "candidate",
          "decision": "WATCH",
          "reason": "局部有效，但稳定性或正交性不足，进入观察名单",
          "closest_active_factor": "vix_z20",
          "best_abs_rankic": 0.0262,
          "mean_abs_rankic": 0.0104,
          "stable_count": 0,
          "mean_consistency": 50.0,
          "best_orthogonality": 0.1137,
          "max_coverage": 81.8,
          "quality_score": 9.79,
          "recommended_action": "保留候选状态，继续观察后续样本",
          "best_horizon": 10,
          "best_rankic": -0.0262,
          "best_ic": -0.0009,
          "q5_q1_ret_diff_pct": -0.08,
          "q5_q1_up_diff_pp": 0.07,
          "stable_halves": false,
          "first_half_rankic": 0.0088,
          "second_half_rankic": -0.0767
        }
      ],
      "reject": [
        {
          "market": "us",
          "factor": "vix_z20_x_vol_surge",
          "family": "macro",
          "status": "candidate",
          "decision": "REJECT_DUPLICATE",
          "reason": "与active因子 vix_z20 高度重叠",
          "closest_active_factor": "vix_z20",
          "best_abs_rankic": 0.0451,
          "mean_abs_rankic": 0.0275,
          "stable_count": 0,
          "mean_consistency": 69.6,
          "best_orthogonality": 0.0355,
          "max_coverage": 83.0,
          "quality_score": 11.23,
          "recommended_action": "记录为重复因子，不建议再次变体试验",
          "best_horizon": 10,
          "best_rankic": -0.0451,
          "best_ic": -0.0257,
          "q5_q1_ret_diff_pct": -1.04,
          "q5_q1_up_diff_pp": -4.07,
          "stable_halves": false,
          "first_half_rankic": 0.0114,
          "second_half_rankic": -0.1116
        },
        {
          "market": "us",
          "factor": "mfdfa_x_high52w",
          "family": "industry",
          "status": "watch",
          "decision": "REJECT",
          "reason": "信号强度不足",
          "closest_active_factor": "mfdfa_width_120d",
          "best_abs_rankic": 0.0219,
          "mean_abs_rankic": 0.0139,
          "stable_count": 0,
          "mean_consistency": 48.2,
          "best_orthogonality": 0.2992,
          "max_coverage": 82.1,
          "quality_score": 11.1,
          "recommended_action": "淘汰，不进入晋升队列",
          "best_horizon": 30,
          "best_rankic": -0.0219,
          "best_ic": -0.0595,
          "q5_q1_ret_diff_pct": -3.13,
          "q5_q1_up_diff_pp": -0.98,
          "stable_halves": false,
          "first_half_rankic": 0.0436,
          "second_half_rankic": -0.0662
        },
        {
          "market": "us",
          "factor": "mfdfa_x_roc10",
          "family": "fractal",
          "status": "watch",
          "decision": "REJECT",
          "reason": "信号强度不足",
          "closest_active_factor": "mfdfa_x_roc20",
          "best_abs_rankic": 0.0215,
          "mean_abs_rankic": 0.0137,
          "stable_count": 0,
          "mean_consistency": 55.7,
          "best_orthogonality": 0.254,
          "max_coverage": 82.1,
          "quality_score": 10.85,
          "recommended_action": "淘汰，不进入晋升队列",
          "best_horizon": 30,
          "best_rankic": 0.0215,
          "best_ic": -0.0023,
          "q5_q1_ret_diff_pct": 1.88,
          "q5_q1_up_diff_pp": 2.67,
          "stable_halves": false,
          "first_half_rankic": 0.0375,
          "second_half_rankic": -0.0006
        },
        {
          "market": "us",
          "factor": "ai_chain_leader_proxy",
          "family": "industry",
          "status": "candidate",
          "decision": "REJECT_DUPLICATE",
          "reason": "与active因子 ROC20 高度重叠",
          "closest_active_factor": "ROC20",
          "best_abs_rankic": 0.0273,
          "mean_abs_rankic": 0.0125,
          "stable_count": 1,
          "mean_consistency": 68.0,
          "best_orthogonality": 0.0962,
          "max_coverage": 87.6,
          "quality_score": 12.49,
          "recommended_action": "记录为重复因子，不建议再次变体试验",
          "best_horizon": 30,
          "best_rankic": -0.0273,
          "best_ic": 0.0753,
          "q5_q1_ret_diff_pct": 0.35,
          "q5_q1_up_diff_pp": 1.18,
          "stable_halves": true,
          "first_half_rankic": -0.069,
          "second_half_rankic": -0.042
        },
        {
          "market": "us",
          "factor": "ai_chain_heat_proxy",
          "family": "industry",
          "status": "candidate",
          "decision": "REJECT_DUPLICATE",
          "reason": "与active因子 ROC20 高度重叠",
          "closest_active_factor": "ROC20",
          "best_abs_rankic": 0.0263,
          "mean_abs_rankic": 0.0215,
          "stable_count": 0,
          "mean_consistency": 69.0,
          "best_orthogonality": 0.0472,
          "max_coverage": 98.0,
          "quality_score": 12.19,
          "recommended_action": "记录为重复因子，不建议再次变体试验",
          "best_horizon": 5,
          "best_rankic": 0.0263,
          "best_ic": 0.0662,
          "q5_q1_ret_diff_pct": 0.59,
          "q5_q1_up_diff_pp": 4.44,
          "stable_halves": false,
          "first_half_rankic": 0.0124,
          "second_half_rankic": 0.0184
        },
        {
          "market": "us",
          "factor": "vix_roc5_x_vol_surge",
          "family": "macro",
          "status": "candidate",
          "decision": "REJECT_DUPLICATE",
          "reason": "与active因子 vix_roc5 高度重叠",
          "closest_active_factor": "vix_roc5",
          "best_abs_rankic": 0.0163,
          "mean_abs_rankic": 0.0139,
          "stable_count": 0,
          "mean_consistency": 62.1,
          "best_orthogonality": 0.0311,
          "max_coverage": 84.2,
          "quality_score": 9.97,
          "recommended_action": "记录为重复因子，不建议再次变体试验",
          "best_horizon": 10,
          "best_rankic": -0.0163,
          "best_ic": 0.0012,
          "q5_q1_ret_diff_pct": -0.13,
          "q5_q1_up_diff_pp": 0.1,
          "stable_halves": false,
          "first_half_rankic": 0.0173,
          "second_half_rankic": -0.0521
        },
        {
          "market": "us",
          "factor": "roc30",
          "family": "trend",
          "status": "candidate",
          "decision": "REJECT",
          "reason": "信号强度不足",
          "closest_active_factor": "ROC20",
          "best_abs_rankic": 0.0179,
          "mean_abs_rankic": 0.0071,
          "stable_count": 0,
          "mean_consistency": 51.4,
          "best_orthogonality": 0.1627,
          "max_coverage": 97.0,
          "quality_score": 11.22,
          "recommended_action": "淘汰，不进入晋升队列",
          "best_horizon": 30,
          "best_rankic": -0.0179,
          "best_ic": 0.022,
          "q5_q1_ret_diff_pct": 1.6,
          "q5_q1_up_diff_pp": 5.14,
          "stable_halves": false,
          "first_half_rankic": -0.0172,
          "second_half_rankic": -0.0646
        },
        {
          "market": "us",
          "factor": "atr_pct_z20",
          "family": "volatility",
          "status": "candidate",
          "decision": "REJECT",
          "reason": "信号强度不足",
          "closest_active_factor": "vol_surge",
          "best_abs_rankic": 0.0113,
          "mean_abs_rankic": 0.0085,
          "stable_count": 0,
          "mean_consistency": 59.7,
          "best_orthogonality": 0.5076,
          "max_coverage": 98.2,
          "quality_score": 13.21,
          "recommended_action": "淘汰，不进入晋升队列",
          "best_horizon": 30,
          "best_rankic": 0.0113,
          "best_ic": 0.01,
          "q5_q1_ret_diff_pct": 0.6,
          "q5_q1_up_diff_pp": 0.41,
          "stable_halves": false,
          "first_half_rankic": 0.0405,
          "second_half_rankic": -0.0018
        },
        {
          "market": "us",
          "factor": "ai_chain_vol_proxy",
          "family": "industry",
          "status": "watch",
          "decision": "REJECT",
          "reason": "信号强度不足",
          "closest_active_factor": "high52w_pos",
          "best_abs_rankic": 0.0088,
          "mean_abs_rankic": 0.0054,
          "stable_count": 0,
          "mean_consistency": 52.3,
          "best_orthogonality": 0.4954,
          "max_coverage": 87.6,
          "quality_score": 11.78,
          "recommended_action": "淘汰，不进入晋升队列",
          "best_horizon": 5,
          "best_rankic": 0.0088,
          "best_ic": 0.0786,
          "q5_q1_ret_diff_pct": 0.55,
          "q5_q1_up_diff_pp": 2.68,
          "stable_halves": false,
          "first_half_rankic": 0.0375,
          "second_half_rankic": -0.0391
        }
      ],
      "counts": {
        "promote_to_trial": 1,
        "watch": 12,
        "reject": 9,
        "total": 22
      },
      "all": [
        {
          "market": "us",
          "factor": "vix_z20_z20",
          "family": "macro",
          "status": "watch",
          "decision": "WATCH",
          "reason": "局部有效且单周期稳定，但整体晋升证据不足，进入观察名单",
          "closest_active_factor": "vix_z20",
          "best_abs_rankic": 0.0451,
          "mean_abs_rankic": 0.0294,
          "stable_count": 1,
          "mean_consistency": 75.5,
          "best_orthogonality": 0.1956,
          "max_coverage": 82.3,
          "quality_score": 14.15,
          "recommended_action": "保留候选状态，继续观察后续样本",
          "best_horizon": 10,
          "best_rankic": -0.0451,
          "best_ic": -0.0408,
          "q5_q1_ret_diff_pct": -1.4,
          "q5_q1_up_diff_pp": -6.41,
          "stable_halves": true,
          "first_half_rankic": -0.0397,
          "second_half_rankic": -0.0588
        },
        {
          "market": "us",
          "factor": "vix_ma20_diff_x_roc20",
          "family": "macro",
          "status": "watch",
          "decision": "PROMOTE_TO_TRIAL",
          "reason": "rankIC、稳定性和正交性均达标，可进入试验池",
          "closest_active_factor": "adx_accel",
          "best_abs_rankic": 0.0419,
          "mean_abs_rankic": 0.0331,
          "stable_count": 3,
          "mean_consistency": 84.7,
          "best_orthogonality": 0.8043,
          "max_coverage": 83.0,
          "quality_score": 21.63,
          "recommended_action": "加入试验回测池，不修改 active 因子池",
          "best_horizon": 5,
          "best_rankic": -0.0419,
          "best_ic": -0.0196,
          "q5_q1_ret_diff_pct": -0.73,
          "q5_q1_up_diff_pp": -6.2,
          "stable_halves": true,
          "first_half_rankic": -0.0306,
          "second_half_rankic": -0.0554
        },
        {
          "market": "us",
          "factor": "high52w_x_vol_surge",
          "family": "trend",
          "status": "candidate",
          "decision": "WATCH",
          "reason": "局部有效，但稳定性或正交性不足，进入观察名单",
          "closest_active_factor": "high52w_pos",
          "best_abs_rankic": 0.05,
          "mean_abs_rankic": 0.0312,
          "stable_count": 0,
          "mean_consistency": 42.1,
          "best_orthogonality": 0.1362,
          "max_coverage": 87.6,
          "quality_score": 12.56,
          "recommended_action": "保留候选状态，继续观察后续样本",
          "best_horizon": 30,
          "best_rankic": 0.05,
          "best_ic": 0.0678,
          "q5_q1_ret_diff_pct": 2.61,
          "q5_q1_up_diff_pp": 10.37,
          "stable_halves": false,
          "first_half_rankic": 0.0181,
          "second_half_rankic": -0.0551
        },
        {
          "market": "us",
          "factor": "gap_ret_15d",
          "family": "behavior",
          "status": "watch",
          "decision": "WATCH",
          "reason": "局部有效，但稳定性或正交性不足，进入观察名单",
          "closest_active_factor": "ROC20",
          "best_abs_rankic": 0.0491,
          "mean_abs_rankic": 0.0361,
          "stable_count": 0,
          "mean_consistency": 61.1,
          "best_orthogonality": 0.3777,
          "max_coverage": 99.3,
          "quality_score": 15.43,
          "recommended_action": "保留候选状态，继续观察后续样本",
          "best_horizon": 10,
          "best_rankic": 0.0491,
          "best_ic": 0.1284,
          "q5_q1_ret_diff_pct": 2.34,
          "q5_q1_up_diff_pp": 6.55,
          "stable_halves": false,
          "first_half_rankic": -0.0392,
          "second_half_rankic": 0.1006
        },
        {
          "market": "us",
          "factor": "vix_z20_x_vol_surge",
          "family": "macro",
          "status": "candidate",
          "decision": "REJECT_DUPLICATE",
          "reason": "与active因子 vix_z20 高度重叠",
          "closest_active_factor": "vix_z20",
          "best_abs_rankic": 0.0451,
          "mean_abs_rankic": 0.0275,
          "stable_count": 0,
          "mean_consistency": 69.6,
          "best_orthogonality": 0.0355,
          "max_coverage": 83.0,
          "quality_score": 11.23,
          "recommended_action": "记录为重复因子，不建议再次变体试验",
          "best_horizon": 10,
          "best_rankic": -0.0451,
          "best_ic": -0.0257,
          "q5_q1_ret_diff_pct": -1.04,
          "q5_q1_up_diff_pp": -4.07,
          "stable_halves": false,
          "first_half_rankic": 0.0114,
          "second_half_rankic": -0.1116
        },
        {
          "market": "us",
          "factor": "vix_z20_x_atr_pct",
          "family": "macro",
          "status": "candidate",
          "decision": "WATCH",
          "reason": "局部有效，但稳定性或正交性不足，进入观察名单",
          "closest_active_factor": "vix_z20",
          "best_abs_rankic": 0.0429,
          "mean_abs_rankic": 0.0202,
          "stable_count": 0,
          "mean_consistency": 78.2,
          "best_orthogonality": 0.1378,
          "max_coverage": 83.1,
          "quality_score": 11.02,
          "recommended_action": "保留候选状态，继续观察后续样本",
          "best_horizon": 10,
          "best_rankic": -0.0429,
          "best_ic": -0.0202,
          "q5_q1_ret_diff_pct": -0.98,
          "q5_q1_up_diff_pp": -3.18,
          "stable_halves": false,
          "first_half_rankic": 0.0115,
          "second_half_rankic": -0.1026
        },
        {
          "market": "us",
          "factor": "gap_ret_10d",
          "family": "behavior",
          "status": "watch",
          "decision": "WATCH",
          "reason": "局部有效，但稳定性或正交性不足，进入观察名单",
          "closest_active_factor": "ROC20",
          "best_abs_rankic": 0.0373,
          "mean_abs_rankic": 0.0274,
          "stable_count": 0,
          "mean_consistency": 61.7,
          "best_orthogonality": 0.4557,
          "max_coverage": 99.5,
          "quality_score": 14.97,
          "recommended_action": "保留候选状态，继续观察后续样本",
          "best_horizon": 30,
          "best_rankic": 0.0373,
          "best_ic": 0.0861,
          "q5_q1_ret_diff_pct": 4.97,
          "q5_q1_up_diff_pp": 7.48,
          "stable_halves": false,
          "first_half_rankic": -0.007,
          "second_half_rankic": 0.0438
        },
        {
          "market": "us",
          "factor": "gap_ret_8d",
          "family": "behavior",
          "status": "watch",
          "decision": "WATCH",
          "reason": "局部有效，但稳定性或正交性不足，进入观察名单",
          "closest_active_factor": "ROC20",
          "best_abs_rankic": 0.036,
          "mean_abs_rankic": 0.0249,
          "stable_count": 0,
          "mean_consistency": 55.6,
          "best_orthogonality": 0.5019,
          "max_coverage": 99.6,
          "quality_score": 14.96,
          "recommended_action": "保留候选状态，继续观察后续样本",
          "best_horizon": 30,
          "best_rankic": 0.036,
          "best_ic": 0.0848,
          "q5_q1_ret_diff_pct": 4.88,
          "q5_q1_up_diff_pp": 7.25,
          "stable_halves": false,
          "first_half_rankic": -0.0047,
          "second_half_rankic": 0.0424
        },
        {
          "market": "us",
          "factor": "roc60",
          "family": "trend",
          "status": "watch",
          "decision": "WATCH",
          "reason": "局部有效，但稳定性或正交性不足，进入观察名单",
          "closest_active_factor": "DIF",
          "best_abs_rankic": 0.0327,
          "mean_abs_rankic": 0.0198,
          "stable_count": 0,
          "mean_consistency": 63.9,
          "best_orthogonality": 0.3328,
          "max_coverage": 94.0,
          "quality_score": 13.04,
          "recommended_action": "保留候选状态，继续观察后续样本",
          "best_horizon": 30,
          "best_rankic": -0.0327,
          "best_ic": 0.0451,
          "q5_q1_ret_diff_pct": 2.73,
          "q5_q1_up_diff_pp": 4.15,
          "stable_halves": false,
          "first_half_rankic": 0.0196,
          "second_half_rankic": -0.1146
        },
        {
          "market": "us",
          "factor": "vol_change_z20",
          "family": "other",
          "status": "watch",
          "decision": "WATCH",
          "reason": "局部有效，但稳定性或正交性不足，进入观察名单",
          "closest_active_factor": "vol_surge",
          "best_abs_rankic": 0.03,
          "mean_abs_rankic": 0.0192,
          "stable_count": 0,
          "mean_consistency": 61.9,
          "best_orthogonality": 0.2188,
          "max_coverage": 98.2,
          "quality_score": 12.83,
          "recommended_action": "保留候选状态，继续观察后续样本",
          "best_horizon": 30,
          "best_rankic": 0.03,
          "best_ic": 0.0482,
          "q5_q1_ret_diff_pct": 3.11,
          "q5_q1_up_diff_pp": 4.61,
          "stable_halves": false,
          "first_half_rankic": -0.014,
          "second_half_rankic": 0.0616
        },
        {
          "market": "us",
          "factor": "gap_ret_5d",
          "family": "behavior",
          "status": "candidate",
          "decision": "WATCH",
          "reason": "局部有效，但稳定性或正交性不足，进入观察名单",
          "closest_active_factor": "-DI",
          "best_abs_rankic": 0.0287,
          "mean_abs_rankic": 0.0162,
          "stable_count": 0,
          "mean_consistency": 50.0,
          "best_orthogonality": 0.5751,
          "max_coverage": 99.7,
          "quality_score": 14.47,
          "recommended_action": "保留候选状态，继续观察后续样本",
          "best_horizon": 30,
          "best_rankic": 0.0287,
          "best_ic": 0.0718,
          "q5_q1_ret_diff_pct": 3.98,
          "q5_q1_up_diff_pp": 5.51,
          "stable_halves": false,
          "first_half_rankic": -0.0064,
          "second_half_rankic": 0.0362
        },
        {
          "market": "us",
          "factor": "gap_ret_3d",
          "family": "behavior",
          "status": "watch",
          "decision": "WATCH",
          "reason": "局部有效，但稳定性或正交性不足，进入观察名单",
          "closest_active_factor": "-DI",
          "best_abs_rankic": 0.0259,
          "mean_abs_rankic": 0.0161,
          "stable_count": 0,
          "mean_consistency": 60.0,
          "best_orthogonality": 0.6318,
          "max_coverage": 99.7,
          "quality_score": 14.74,
          "recommended_action": "保留候选状态，继续观察后续样本",
          "best_horizon": 30,
          "best_rankic": 0.0259,
          "best_ic": 0.0566,
          "q5_q1_ret_diff_pct": 3.72,
          "q5_q1_up_diff_pp": 3.33,
          "stable_halves": false,
          "first_half_rankic": 0.0023,
          "second_half_rankic": 0.0296
        },
        {
          "market": "us",
          "factor": "mfdfa_x_high52w",
          "family": "industry",
          "status": "watch",
          "decision": "REJECT",
          "reason": "信号强度不足",
          "closest_active_factor": "mfdfa_width_120d",
          "best_abs_rankic": 0.0219,
          "mean_abs_rankic": 0.0139,
          "stable_count": 0,
          "mean_consistency": 48.2,
          "best_orthogonality": 0.2992,
          "max_coverage": 82.1,
          "quality_score": 11.1,
          "recommended_action": "淘汰，不进入晋升队列",
          "best_horizon": 30,
          "best_rankic": -0.0219,
          "best_ic": -0.0595,
          "q5_q1_ret_diff_pct": -3.13,
          "q5_q1_up_diff_pp": -0.98,
          "stable_halves": false,
          "first_half_rankic": 0.0436,
          "second_half_rankic": -0.0662
        },
        {
          "market": "us",
          "factor": "mfdfa_x_roc10",
          "family": "fractal",
          "status": "watch",
          "decision": "REJECT",
          "reason": "信号强度不足",
          "closest_active_factor": "mfdfa_x_roc20",
          "best_abs_rankic": 0.0215,
          "mean_abs_rankic": 0.0137,
          "stable_count": 0,
          "mean_consistency": 55.7,
          "best_orthogonality": 0.254,
          "max_coverage": 82.1,
          "quality_score": 10.85,
          "recommended_action": "淘汰，不进入晋升队列",
          "best_horizon": 30,
          "best_rankic": 0.0215,
          "best_ic": -0.0023,
          "q5_q1_ret_diff_pct": 1.88,
          "q5_q1_up_diff_pp": 2.67,
          "stable_halves": false,
          "first_half_rankic": 0.0375,
          "second_half_rankic": -0.0006
        },
        {
          "market": "us",
          "factor": "vol_change_x_high52w",
          "family": "industry",
          "status": "watch",
          "decision": "WATCH",
          "reason": "局部有效且单周期稳定，但整体晋升证据不足，进入观察名单",
          "closest_active_factor": "vol_surge",
          "best_abs_rankic": 0.032,
          "mean_abs_rankic": 0.0246,
          "stable_count": 1,
          "mean_consistency": 59.3,
          "best_orthogonality": 0.1183,
          "max_coverage": 87.6,
          "quality_score": 13.81,
          "recommended_action": "保留候选状态，继续观察后续样本",
          "best_horizon": 30,
          "best_rankic": 0.032,
          "best_ic": 0.0767,
          "q5_q1_ret_diff_pct": 3.39,
          "q5_q1_up_diff_pp": 3.61,
          "stable_halves": true,
          "first_half_rankic": 0.0424,
          "second_half_rankic": 0.0549
        },
        {
          "market": "us",
          "factor": "ai_chain_leader_proxy",
          "family": "industry",
          "status": "candidate",
          "decision": "REJECT_DUPLICATE",
          "reason": "与active因子 ROC20 高度重叠",
          "closest_active_factor": "ROC20",
          "best_abs_rankic": 0.0273,
          "mean_abs_rankic": 0.0125,
          "stable_count": 1,
          "mean_consistency": 68.0,
          "best_orthogonality": 0.0962,
          "max_coverage": 87.6,
          "quality_score": 12.49,
          "recommended_action": "记录为重复因子，不建议再次变体试验",
          "best_horizon": 30,
          "best_rankic": -0.0273,
          "best_ic": 0.0753,
          "q5_q1_ret_diff_pct": 0.35,
          "q5_q1_up_diff_pp": 1.18,
          "stable_halves": true,
          "first_half_rankic": -0.069,
          "second_half_rankic": -0.042
        },
        {
          "market": "us",
          "factor": "ai_chain_heat_proxy",
          "family": "industry",
          "status": "candidate",
          "decision": "REJECT_DUPLICATE",
          "reason": "与active因子 ROC20 高度重叠",
          "closest_active_factor": "ROC20",
          "best_abs_rankic": 0.0263,
          "mean_abs_rankic": 0.0215,
          "stable_count": 0,
          "mean_consistency": 69.0,
          "best_orthogonality": 0.0472,
          "max_coverage": 98.0,
          "quality_score": 12.19,
          "recommended_action": "记录为重复因子，不建议再次变体试验",
          "best_horizon": 5,
          "best_rankic": 0.0263,
          "best_ic": 0.0662,
          "q5_q1_ret_diff_pct": 0.59,
          "q5_q1_up_diff_pp": 4.44,
          "stable_halves": false,
          "first_half_rankic": 0.0124,
          "second_half_rankic": 0.0184
        },
        {
          "market": "us",
          "factor": "vix_z20_x_high52w",
          "family": "macro",
          "status": "candidate",
          "decision": "WATCH",
          "reason": "局部有效，但稳定性或正交性不足，进入观察名单",
          "closest_active_factor": "vix_z20",
          "best_abs_rankic": 0.0262,
          "mean_abs_rankic": 0.0104,
          "stable_count": 0,
          "mean_consistency": 50.0,
          "best_orthogonality": 0.1137,
          "max_coverage": 81.8,
          "quality_score": 9.79,
          "recommended_action": "保留候选状态，继续观察后续样本",
          "best_horizon": 10,
          "best_rankic": -0.0262,
          "best_ic": -0.0009,
          "q5_q1_ret_diff_pct": -0.08,
          "q5_q1_up_diff_pp": 0.07,
          "stable_halves": false,
          "first_half_rankic": 0.0088,
          "second_half_rankic": -0.0767
        },
        {
          "market": "us",
          "factor": "vix_roc5_x_vol_surge",
          "family": "macro",
          "status": "candidate",
          "decision": "REJECT_DUPLICATE",
          "reason": "与active因子 vix_roc5 高度重叠",
          "closest_active_factor": "vix_roc5",
          "best_abs_rankic": 0.0163,
          "mean_abs_rankic": 0.0139,
          "stable_count": 0,
          "mean_consistency": 62.1,
          "best_orthogonality": 0.0311,
          "max_coverage": 84.2,
          "quality_score": 9.97,
          "recommended_action": "记录为重复因子，不建议再次变体试验",
          "best_horizon": 10,
          "best_rankic": -0.0163,
          "best_ic": 0.0012,
          "q5_q1_ret_diff_pct": -0.13,
          "q5_q1_up_diff_pp": 0.1,
          "stable_halves": false,
          "first_half_rankic": 0.0173,
          "second_half_rankic": -0.0521
        },
        {
          "market": "us",
          "factor": "roc30",
          "family": "trend",
          "status": "candidate",
          "decision": "REJECT",
          "reason": "信号强度不足",
          "closest_active_factor": "ROC20",
          "best_abs_rankic": 0.0179,
          "mean_abs_rankic": 0.0071,
          "stable_count": 0,
          "mean_consistency": 51.4,
          "best_orthogonality": 0.1627,
          "max_coverage": 97.0,
          "quality_score": 11.22,
          "recommended_action": "淘汰，不进入晋升队列",
          "best_horizon": 30,
          "best_rankic": -0.0179,
          "best_ic": 0.022,
          "q5_q1_ret_diff_pct": 1.6,
          "q5_q1_up_diff_pp": 5.14,
          "stable_halves": false,
          "first_half_rankic": -0.0172,
          "second_half_rankic": -0.0646
        },
        {
          "market": "us",
          "factor": "atr_pct_z20",
          "family": "volatility",
          "status": "candidate",
          "decision": "REJECT",
          "reason": "信号强度不足",
          "closest_active_factor": "vol_surge",
          "best_abs_rankic": 0.0113,
          "mean_abs_rankic": 0.0085,
          "stable_count": 0,
          "mean_consistency": 59.7,
          "best_orthogonality": 0.5076,
          "max_coverage": 98.2,
          "quality_score": 13.21,
          "recommended_action": "淘汰，不进入晋升队列",
          "best_horizon": 30,
          "best_rankic": 0.0113,
          "best_ic": 0.01,
          "q5_q1_ret_diff_pct": 0.6,
          "q5_q1_up_diff_pp": 0.41,
          "stable_halves": false,
          "first_half_rankic": 0.0405,
          "second_half_rankic": -0.0018
        },
        {
          "market": "us",
          "factor": "ai_chain_vol_proxy",
          "family": "industry",
          "status": "watch",
          "decision": "REJECT",
          "reason": "信号强度不足",
          "closest_active_factor": "high52w_pos",
          "best_abs_rankic": 0.0088,
          "mean_abs_rankic": 0.0054,
          "stable_count": 0,
          "mean_consistency": 52.3,
          "best_orthogonality": 0.4954,
          "max_coverage": 87.6,
          "quality_score": 11.78,
          "recommended_action": "淘汰，不进入晋升队列",
          "best_horizon": 5,
          "best_rankic": 0.0088,
          "best_ic": 0.0786,
          "q5_q1_ret_diff_pct": 0.55,
          "q5_q1_up_diff_pp": 2.68,
          "stable_halves": false,
          "first_half_rankic": 0.0375,
          "second_half_rankic": -0.0391
        }
      ]
    }
  },
  "promotion_queue": [
    {
      "market": "a",
      "factor": "earnings_accel_proxy",
      "family": "industry",
      "status": "candidate",
      "decision": "PROMOTE_TO_TRIAL",
      "reason": "rankIC、稳定性和正交性均达标，可进入试验池",
      "closest_active_factor": "rev_growth_accel",
      "best_abs_rankic": 0.1626,
      "mean_abs_rankic": 0.1154,
      "stable_count": 3,
      "mean_consistency": 100.0,
      "best_orthogonality": 0.4273,
      "max_coverage": 100.0,
      "quality_score": 29.68,
      "recommended_action": "加入试验回测池，不修改 active 因子池",
      "best_horizon": 30,
      "best_rankic": -0.1626,
      "best_ic": -0.0589,
      "q5_q1_ret_diff_pct": -9.21,
      "q5_q1_up_diff_pp": -18.83,
      "stable_halves": true,
      "first_half_rankic": -0.0585,
      "second_half_rankic": -0.2893
    },
    {
      "market": "us",
      "factor": "vix_ma20_diff_x_roc20",
      "family": "macro",
      "status": "watch",
      "decision": "PROMOTE_TO_TRIAL",
      "reason": "rankIC、稳定性和正交性均达标，可进入试验池",
      "closest_active_factor": "adx_accel",
      "best_abs_rankic": 0.0419,
      "mean_abs_rankic": 0.0331,
      "stable_count": 3,
      "mean_consistency": 84.7,
      "best_orthogonality": 0.8043,
      "max_coverage": 83.0,
      "quality_score": 21.63,
      "recommended_action": "加入试验回测池，不修改 active 因子池",
      "best_horizon": 5,
      "best_rankic": -0.0419,
      "best_ic": -0.0196,
      "q5_q1_ret_diff_pct": -0.73,
      "q5_q1_up_diff_pp": -6.2,
      "stable_halves": true,
      "first_half_rankic": -0.0306,
      "second_half_rankic": -0.0554
    },
    {
      "market": "a",
      "factor": "gap_ret_20d",
      "family": "behavior",
      "status": "candidate",
      "decision": "PROMOTE_TO_TRIAL",
      "reason": "rankIC、稳定性和正交性均达标，可进入试验池",
      "closest_active_factor": "gap_ret_10d",
      "best_abs_rankic": 0.0712,
      "mean_abs_rankic": 0.0472,
      "stable_count": 2,
      "mean_consistency": 78.3,
      "best_orthogonality": 0.2778,
      "max_coverage": 98.4,
      "quality_score": 19.95,
      "recommended_action": "加入试验回测池，不修改 active 因子池",
      "best_horizon": 10,
      "best_rankic": -0.0712,
      "best_ic": -0.0332,
      "q5_q1_ret_diff_pct": -1.24,
      "q5_q1_up_diff_pp": -10.47,
      "stable_halves": true,
      "first_half_rankic": -0.1045,
      "second_half_rankic": -0.0727
    }
  ]
}